rainstorm/__init__.py
rainstorm/geometric_classes.py
rainstorm/utils.py
rainstorm/BehavioralLabeler/BehavioralLabeler.py
rainstorm/BehavioralLabeler/__init__.py
rainstorm/BehavioralLabeler/__main__.py
rainstorm/BehavioralLabeler/gui/__init__.py
rainstorm/BehavioralLabeler/gui/frame_display.py
rainstorm/BehavioralLabeler/gui/main_menu_window.py
rainstorm/BehavioralLabeler/gui/timeline_window.py
rainstorm/BehavioralLabeler/src/__init__.py
rainstorm/BehavioralLabeler/src/app.py
rainstorm/BehavioralLabeler/src/config.py
rainstorm/BehavioralLabeler/src/label_manager.py
rainstorm/BehavioralLabeler/src/logger.py
rainstorm/BehavioralLabeler/src/utils.py
rainstorm/BehavioralLabeler/src/video_processor.py
rainstorm/DrawROIs/DrawROIs.py
rainstorm/DrawROIs/__init__.py
rainstorm/DrawROIs/__main__.py
rainstorm/DrawROIs/gui/__init__.py
rainstorm/DrawROIs/gui/dialogs.py
rainstorm/DrawROIs/gui/main_window.py
rainstorm/DrawROIs/src/__init__.py
rainstorm/DrawROIs/src/app.py
rainstorm/DrawROIs/src/config.py
rainstorm/DrawROIs/src/logger.py
rainstorm/DrawROIs/src/core/__init__.py
rainstorm/DrawROIs/src/core/drawing_utils.py
rainstorm/DrawROIs/src/core/roi_manager.py
rainstorm/DrawROIs/src/core/video_processor.py
rainstorm/VideoHandling/VideoHandling.py
rainstorm/VideoHandling/__init__.py
rainstorm/VideoHandling/__main__.py
rainstorm/VideoHandling/components/__init__.py
rainstorm/VideoHandling/components/aligner.py
rainstorm/VideoHandling/components/cropper.py
rainstorm/VideoHandling/components/rotator.py
rainstorm/VideoHandling/components/trimmer.py
rainstorm/VideoHandling/gui/__init__.py
rainstorm/VideoHandling/gui/application.py
rainstorm/VideoHandling/gui/gui_utils.py
rainstorm/VideoHandling/tools/__init__.py
rainstorm/VideoHandling/tools/config.py
rainstorm/VideoHandling/tools/image_utils.py
rainstorm/VideoHandling/tools/logger.py
rainstorm/VideoHandling/tools/video_manager.py
rainstorm/VideoHandling/tools/video_processor.py
rainstorm/geometric_analysis/__init__.py
rainstorm-1.0.11.dist-info/licenses/LICENSE
rainstorm-1.0.11.dist-info/METADATA
rainstorm-1.0.11.dist-info/WHEEL
rainstorm-1.0.11.dist-info/top_level.txt
rainstorm-1.0.11.dist-info/RECORD
