Metadata-Version: 2.4
Name: rainstorm
Version: 1.0.11
Summary: Real & Artificial Intelligence for Neuroscience – Simple Tracker for Object Recognition Memory
Home-page: https://github.com/sdhers/RAINSTORM
Author: Santiago D'hers
Author-email: sdhers@fbmc.fcen.uba.ar
License: MIT
Classifier: Programming Language :: Python :: 3.9
Classifier: Operating System :: OS Independent
Classifier: Topic :: Scientific/Engineering :: Artificial Intelligence
Classifier: Intended Audience :: Science/Research
Requires-Python: >=3.9
License-File: LICENSE
Requires-Dist: h5py==3.12.1
Requires-Dist: keras==2.10.0
Requires-Dist: keyboard==0.13.5
Requires-Dist: matplotlib==3.9.3
Requires-Dist: numpy==1.25.2
Requires-Dist: opencv-python==4.10.0.84
Requires-Dist: pandas==2.0.3
Requires-Dist: plotly==5.24.1
Requires-Dist: PyYAML==6.0.2
Requires-Dist: ruamel.yaml==0.17.21
Requires-Dist: scikit-learn==1.6.0
Requires-Dist: scipy==1.13.1
Requires-Dist: seaborn==0.13.2
Requires-Dist: tables==3.9.2
Requires-Dist: tensorflow==2.10.1
Requires-Dist: tqdm==4.67.1
Requires-Dist: customtkinter==5.2.2
Dynamic: author
Dynamic: author-email
Dynamic: classifier
Dynamic: description
Dynamic: description-content-type
Dynamic: home-page
Dynamic: license
Dynamic: license-file
Dynamic: requires-dist
Dynamic: requires-python
Dynamic: summary
